adafruit_vl53l4cd.py
adafruit_circuitpython_vl53l4cd-1.3.4.dist-info/licenses/LICENSE
adafruit_circuitpython_vl53l4cd-1.3.4.dist-info/METADATA
adafruit_circuitpython_vl53l4cd-1.3.4.dist-info/WHEEL
adafruit_circuitpython_vl53l4cd-1.3.4.dist-info/top_level.txt
adafruit_circuitpython_vl53l4cd-1.3.4.dist-info/RECORD
