Metadata-Version: 2.4
Name: adafruit-circuitpython-vl53l4cd
Version: 1.3.4
Summary: CircuitPython helper library for the VL53L4CD time of flight distance sensor.
Author-email: Adafruit Industries <circuitpython@adafruit.com>
License: MIT
Project-URL: Homepage, https://github.com/adafruit/Adafruit_CircuitPython_VL53L4CD.git
Keywords: adafruit,blinka,circuitpython,micropython,vl53l4cd,distance
Classifier: Intended Audience :: Developers
Classifier: Topic :: Software Development :: Libraries
Classifier: Topic :: Software Development :: Embedded Systems
Classifier: Topic :: System :: Hardware
Classifier: License :: OSI Approved :: MIT License
Classifier: Programming Language :: Python :: 3
License-File: LICENSE
Requires-Dist: Adafruit-Blinka
Requires-Dist: adafruit-circuitpython-busdevice
Provides-Extra: optional
Dynamic: license-file
